{
  "table_name": "ARPB_TX_MATCH_HX",
  "description": "Matching History Transaction Related Items.  A line is added to this related group whenever two transactions are matched together.",
  "primary_key": {
    "column_name": "TX_ID",
    "ordinal_position": "1"
  },
  "columns": [
    {
      "index": 2,
      "name": "TX_ID",
      "type": "NUMERIC",
      "discontinued": false,
      "description": "The unique identifier for the transaction record."
    },
    {
      "index": 7,
      "name": "LINE",
      "type": "INTEGER",
      "discontinued": false,
      "description": "The line number for the information associated with this record. Multiple pieces of information can be associated with this record."
    },
    {
      "index": 12,
      "name": "MTCH_TX_HX_DT",
      "type": "DATETIME",
      "discontinued": false,
      "description": "This item stores the date that a transaction was matched to this transaction."
    },
    {
      "index": 17,
      "name": "MTCH_TX_HX_ID",
      "type": "NUMERIC",
      "discontinued": false,
      "description": "This item stores the transaction that this transaction was matched to.  If the MTCH_TX_HX_UN_DT is null, then the transaction is still currently matched to this transaction."
    },
    {
      "index": 22,
      "name": "MTCH_TX_HX_AMT",
      "type": "NUMERIC",
      "discontinued": false,
      "description": "This item stores the (insurance+self-pay) amount for which this transaction is matched to the transaction in column MTCH_TX_HX_ID."
    },
    {
      "index": 27,
      "name": "MTCH_TX_HX_INS_AMT",
      "type": "NUMERIC",
      "discontinued": false,
      "description": "This item stores the insurance amount for which this transaction is matched to the transaction in column MTCH_TX_HX_ID."
    },
    {
      "index": 32,
      "name": "MTCH_TX_HX_PAT_AMT",
      "type": "NUMERIC",
      "discontinued": false,
      "description": "This item stores the self-pay amount for which this transaction is matched to the transaction in column MTCH_TX_HX_ID."
    },
    {
      "index": 37,
      "name": "MTCH_TX_HX_COMMENT",
      "type": "VARCHAR",
      "discontinued": false,
      "description": "This item holds the comment for the matching of this transaction to the transaction in column MTCH_TX_HX_ID.  This item is typically only populated by the system and not user entered comments."
    },
    {
      "index": 42,
      "name": "MTCH_TX_HX_UN_DT",
      "type": "DATETIME",
      "discontinued": false,
      "description": "This item holds the date that the transaction was unmatched from the transaction in column MTCH_TX_HX_ID."
    },
    {
      "index": 47,
      "name": "MTCH_TX_HX_D_CVG_ID",
      "type": "NUMERIC",
      "discontinued": false,
      "description": "This item stores the coverage ID at the time that the transaction was matched to the transaction in column MTCH_TX_HX_ID."
    },
    {
      "index": 52,
      "name": "MTCH_TX_HX_DSUSR_ID",
      "type": "VARCHAR",
      "discontinued": false,
      "description": "This item stores the users who matched this transaction to the transaction from column MTCH_TX_HX_ID."
    },
    {
      "index": 57,
      "name": "MTCH_TX_HX_UDUSR_ID",
      "type": "VARCHAR",
      "discontinued": false,
      "description": "This item stores the user that unmatched this transaction from the transaction in the MTCH_TX_HX_ID column."
    },
    {
      "index": 62,
      "name": "MTCH_TX_HX_INV_NUM",
      "type": "VARCHAR",
      "discontinued": false,
      "description": "This item stores the invoice associated with the debit transaction in the matching group."
    },
    {
      "index": 67,
      "name": "MTCH_TX_HX_UN_COM",
      "type": "VARCHAR",
      "discontinued": false,
      "description": "This item stores the comment entered when the transaction is undistributed."
    },
    {
      "index": 72,
      "name": "MTCH_TX_HX_UN_CV_ID",
      "type": "NUMERIC",
      "discontinued": false,
      "description": "This is the coverage of the debit transaction at the time of unmatch."
    },
    {
      "index": 77,
      "name": "MTCH_TX_HX_LINE",
      "type": "INTEGER",
      "discontinued": false,
      "description": "This item stores the corresponding line from the matched transaction."
    },
    {
      "index": 82,
      "name": "MTCH_TX_HX_DTTM",
      "type": "DATETIME (UTC)",
      "discontinued": false,
      "description": "The UTC date and time the transaction was matched."
    },
    {
      "index": 87,
      "name": "MTCH_TX_HX_UN_DTTM",
      "type": "DATETIME (UTC)",
      "discontinued": false,
      "description": "The UTC date and time the transaction was unmatched."
    }
  ]
}
