{
  "name": "ATB_ROOT",
  "description": "ATB ROOT Data.",
  "primaryKey": [
    {
      "columnName": "AUTH_BUNDLE_ID",
      "ordinalPosition": 1
    }
  ],
  "columns": [
    {
      "ordinalPosition": 1,
      "name": "AUTH_BUNDLE_ID",
      "type": "NUMERIC",
      "discontinued": false,
      "description": "The unique identifier (.1 item) for the authorization bundle record."
    },
    {
      "ordinalPosition": 2,
      "name": "PAT_ID",
      "type": "VARCHAR",
      "discontinued": false,
      "description": "Patient for ATB"
    },
    {
      "ordinalPosition": 3,
      "name": "REFERRAL_ID",
      "type": "NUMERIC",
      "discontinued": false,
      "description": "Associated Authorization Referral"
    },
    {
      "ordinalPosition": 4,
      "name": "COVERAGE_ID",
      "type": "NUMERIC",
      "discontinued": false,
      "description": "Coverages associated with the ATB."
    }
  ]
}
