{
  "table_name": "CLARITY_ROM",
  "description": "This table reflects the information in the Hospital Rooms (ROM) master file.",
  "primary_key": {
    "column_name": "ROOM_CSN_ID",
    "ordinal_position": "1"
  },
  "columns": [
    {
      "index": 2,
      "name": "ROOM_CSN_ID",
      "type": "NUMERIC",
      "discontinued": false,
      "description": "The serial number for the room contact of the room record. This number is unique across all room contacts in the system."
    },
    {
      "index": 7,
      "name": "ROOM_NAME",
      "type": "VARCHAR",
      "discontinued": false,
      "description": "The name of the room."
    }
  ]
}
