{
  "table_name": "CUST_SERVICE_NOTES",
  "description": "The CUST_SERVICE_NOTES table contains information about the notes that are attached to each customer service communication.",
  "primary_key": {
    "column_name": "NOTE_ID",
    "ordinal_position": "1"
  },
  "columns": [
    {
      "index": 2,
      "name": "NOTE_ID",
      "type": "VARCHAR",
      "discontinued": false,
      "description": "The unique ID of the note attached to a customer service communication."
    },
    {
      "index": 7,
      "name": "LINE",
      "type": "INTEGER",
      "discontinued": false,
      "description": "The line number for the information associated with this record. Multiple pieces of information can be associated with this record."
    },
    {
      "index": 12,
      "name": "NOTE_DATE",
      "type": "DATETIME",
      "discontinued": false,
      "description": "The date when the note was created. This column contains date information only. Column NOTE_DATETIME holds date and time information."
    },
    {
      "index": 17,
      "name": "NOTE_USER_ID",
      "type": "VARCHAR",
      "discontinued": false,
      "description": "The unique ID of the user who created the note."
    },
    {
      "index": 22,
      "name": "RECORD_ID",
      "type": "NUMERIC",
      "discontinued": false,
      "description": "The unique identifier for the customer service communication."
    }
  ]
}
