{
  "table_name": "CVG_RTE_QUERY",
  "description": "Table for Eligibility coverage queries.",
  "primary_key": {
    "column_name": "CVG_ID",
    "ordinal_position": "1"
  },
  "columns": [
    {
      "index": 2,
      "name": "CVG_ID",
      "type": "NUMERIC",
      "discontinued": false,
      "description": "The unique identifier of the coverage (CVG) record."
    },
    {
      "index": 7,
      "name": "LINE",
      "type": "INTEGER",
      "discontinued": false,
      "description": "The line number for the information associated with this record. Multiple pieces of information can be associated with this record."
    },
    {
      "index": 12,
      "name": "SENT_INST",
      "type": "VARCHAR",
      "discontinued": false,
      "description": "The time an eligibility response was sent."
    },
    {
      "index": 17,
      "name": "RCVD_INST",
      "type": "VARCHAR",
      "discontinued": false,
      "description": "The time an eligibility response was received."
    },
    {
      "index": 22,
      "name": "RESP_ID",
      "type": "VARCHAR",
      "discontinued": false,
      "description": "The ID of the linked note (HNO) record for the response text."
    },
    {
      "index": 27,
      "name": "RESP_FILED_YN",
      "type": "VARCHAR",
      "discontinued": false,
      "description": "This item flags if the response data was filed.\n\n\nMay contain organization-specific values: No\n\n\n Category Entries: \n\n\nYes\n\n\nNo"
    },
    {
      "index": 36,
      "name": "HGEN_INX",
      "type": "NUMERIC",
      "discontinued": false,
      "description": "Index to HGEN global for message info. Packed version of CVG 8550 HGEN INDEX"
    },
    {
      "index": 41,
      "name": "PAT_ID",
      "type": "VARCHAR",
      "discontinued": false,
      "description": "Record the patient ID of the member for the particular response message."
    },
    {
      "index": 46,
      "name": "QUERY_DATE",
      "type": "DATETIME",
      "discontinued": false,
      "description": "A record of the service date queried."
    },
    {
      "index": 51,
      "name": "SENT_TRUE_INST_DTTM",
      "type": "DATETIME (UTC)",
      "discontinued": false,
      "description": "The time an eligibility response was sent, in instance format."
    },
    {
      "index": 56,
      "name": "RESPONSE_REG_STATUS_C_NAME",
      "type": "VARCHAR",
      "discontinued": false,
      "description": "This contains the verification status associated with a specific RTE (real-time eligibility) Response.\n\n\nMay contain organization-specific values: Yes"
    }
  ]
}
