{
  "table_name": "ED_IEV_EVENT_INFO_FLAGS",
  "description": "Holds the Event Value Flags for Events Database (IEV) Events.",
  "primary_key": {
    "column_name": "EVENT_ID",
    "ordinal_position": "1"
  },
  "columns": [
    {
      "index": 2,
      "name": "EVENT_ID",
      "type": "VARCHAR",
      "discontinued": false,
      "description": "The unique identifier for the event record."
    },
    {
      "index": 7,
      "name": "GROUP_LINE",
      "type": "INTEGER",
      "discontinued": false,
      "description": "The line number for the information associated with this event."
    },
    {
      "index": 12,
      "name": "VALUE_LINE",
      "type": "INTEGER",
      "discontinued": false,
      "description": "The line number of one of the multiple flags associated with a specific group of data within this record."
    },
    {
      "index": 17,
      "name": "EVENT_FLAGS_C_NAME",
      "type": "VARCHAR",
      "discontinued": false,
      "description": "The flags for a value that was added as an ED course comment, such as \"abnormal\" or \"critical\" for a lab result value.\n\n\nMay contain organization-specific values: No\n\n\n Category Entries: \n\n\n(none)\n\n\nAbnormal Value\n\n\nCritical Value\n\n\nSignificant\n\n\nDiscrepant\n\n\nAbnormally Low Value\n\n\nAbnormally High Value\n\n\nCritically Low Value\n\n\nCritically High Val\n\n\nAbnormal Order\n\n\nCritical Order\n\n\nPast Result"
    }
  ]
}
