{
  "table_name": "FEE_SCHEDULE_MAP",
  "description": "The FEE_SCHEDULE_MAP table contains basic information about the fee schedule map that is used to select a fee schedule and conversion factor table per geographic area.",
  "primary_key": {
    "column_name": "FEE_SCHEDULE_MAP_ID",
    "ordinal_position": "1"
  },
  "columns": [
    {
      "index": 2,
      "name": "FEE_SCHEDULE_MAP_ID",
      "type": "NUMERIC",
      "discontinued": false,
      "description": "The unique identifier for the fee schedule map record."
    },
    {
      "index": 7,
      "name": "FEE_SCHEDULE_MAP_NAME",
      "type": "VARCHAR",
      "discontinued": false,
      "description": "The name for the fee schedule map record."
    }
  ]
}
