{
  "table_name": "FOL_INFO",
  "description": "Follow-up Workqueue general items table.",
  "primary_key": {
    "column_name": "FOL_ID",
    "ordinal_position": "1"
  },
  "columns": [
    {
      "index": 2,
      "name": "FOL_ID",
      "type": "NUMERIC",
      "discontinued": false,
      "description": "This is the follow up record ID."
    },
    {
      "index": 7,
      "name": "TRANSACTION_ID",
      "type": "NUMERIC",
      "discontinued": false,
      "description": "Link to the follow-up records corresponding charge record."
    }
  ]
}
