{
  "table_name": "LNO_LAB_MAIN",
  "description": "Primary Lab Result Report (LNO) data.",
  "primary_key": {
    "column_name": "RECORD_ID",
    "ordinal_position": "1"
  },
  "columns": [
    {
      "index": 2,
      "name": "RECORD_ID",
      "type": "NUMERIC",
      "discontinued": false,
      "description": "The unique identifier for the LNO record."
    },
    {
      "index": 7,
      "name": "LAB_REP_DATA_DATE",
      "type": "DATETIME",
      "discontinued": false,
      "description": "The date the report data was filled into the Patient Summary Extract (LNO) record. This usually contains the report date."
    },
    {
      "index": 12,
      "name": "LAB_ID",
      "type": "VARCHAR",
      "discontinued": false,
      "description": "The lab record ID that this Patient Summary Extract (LNO) is linked to."
    },
    {
      "index": 17,
      "name": "DEPT_ID",
      "type": "NUMERIC",
      "discontinued": false,
      "description": "Stores the encounter department"
    },
    {
      "index": 22,
      "name": "LAB_REPORT_TYPE_C_NAME",
      "type": "VARCHAR",
      "discontinued": false,
      "description": "The result report type category number for the result report.\n\n\nMay contain organization-specific values: No\n\n\n Category Entries: \n\n\nSingle Specimen Report\n\n\nEnd of Day Report\n\n\nEnd of Week Report\n\n\nDischarge Report\n\n\nSTAT Report\n\n\nEncounter Level Report\n\n\nMultiple Encounter Report\n\n\nHold till all final Report\n\n\nAny Final Report\n\n\nAny Prelim or Final Report\n\n\nFinal Summary Report\n\n\nAdhoc Report\n\n\nMaster Record"
    },
    {
      "index": 42,
      "name": "REQUISITION_ID",
      "type": "NUMERIC",
      "discontinued": false,
      "description": "Stores the requisition record if any for which this record was created."
    },
    {
      "index": 47,
      "name": "SUBMITTER_ID",
      "type": "NUMERIC",
      "discontinued": false,
      "description": "This is the submitter associated with the specimen on the report."
    },
    {
      "index": 52,
      "name": "SUBMITTER_ID_RECORD_NAME",
      "type": "VARCHAR",
      "discontinued": false,
      "description": "The name of the submitter record."
    },
    {
      "index": 57,
      "name": "REQ_GRP_ID",
      "type": "NUMERIC",
      "discontinued": false,
      "description": "This is the reference lab patient associated with the specimen on the report."
    },
    {
      "index": 62,
      "name": "CASE_ID",
      "type": "NUMERIC",
      "discontinued": false,
      "description": "Stores the case record for which this record was created."
    }
  ]
}
