{
  "table_name": "MYC_CONVO_ABT_PAT_ENC",
  "description": "Contains the list of encounters that this message is about. This is not the encounters created as a result of sending the message. For those encounters, see MYC_CONVO_ENCS.",
  "primary_key": {
    "column_name": "THREAD_ID",
    "ordinal_position": "1"
  },
  "columns": [
    {
      "index": 2,
      "name": "THREAD_ID",
      "type": "NUMERIC",
      "discontinued": false,
      "description": "The unique identifier (.1 item) for the thread record."
    },
    {
      "index": 7,
      "name": "LINE",
      "type": "INTEGER",
      "discontinued": false,
      "description": "The line number for the information associated with this record. Multiple pieces of information can be associated with this record."
    },
    {
      "index": 12,
      "name": "PAT_ENC_CSN_ID",
      "type": "NUMERIC",
      "discontinued": false,
      "description": "This is the visit encounter that this conversation is about."
    }
  ]
}
