{
  "table_name": "NOTE_ATTACHED_IMG",
  "description": "Stores the document IDs of images attached to the note from Canto.",
  "primary_key": {
    "column_name": "NOTE_ID",
    "ordinal_position": "1"
  },
  "columns": [
    {
      "index": 2,
      "name": "NOTE_ID",
      "type": "VARCHAR",
      "discontinued": false,
      "description": "The unique identifier for the note record."
    },
    {
      "index": 7,
      "name": "LINE",
      "type": "INTEGER",
      "discontinued": false,
      "description": "The line number for the attached image associated with this note. Multiple pieces of information can be associated with this record."
    },
    {
      "index": 12,
      "name": "NOTE_IMG_DOC_ID",
      "type": "VARCHAR",
      "discontinued": false,
      "description": "Stores the storage ID of images attached to the note from Canto."
    }
  ]
}
