{
  "table_name": "ORDER_LOOKUP_REC",
  "description": "This table extracts the information about Medication/Procedure/Smart Group record included in the order lookup record.",
  "primary_key": {
    "column_name": "ORDER_LOOKUP_ID",
    "ordinal_position": "1"
  },
  "columns": [
    {
      "index": 2,
      "name": "ORDER_LOOKUP_ID",
      "type": "NUMERIC",
      "discontinued": false,
      "description": "The unique identifier (.1 item) for the order panel record."
    },
    {
      "index": 7,
      "name": "ORDER_LOOKUP_NAME",
      "type": "VARCHAR",
      "discontinued": false,
      "description": "The name (.2 item) for the order panel record."
    }
  ]
}
