{
  "table_name": "ORDER_SUMMARY",
  "description": "Contains the summary for an order that has been signed.",
  "primary_key": {
    "column_name": "ORDER_ID",
    "ordinal_position": "1"
  },
  "columns": [
    {
      "index": 2,
      "name": "ORDER_ID",
      "type": "NUMERIC",
      "discontinued": false,
      "description": "The unique identifier for the order record."
    },
    {
      "index": 7,
      "name": "LINE",
      "type": "INTEGER",
      "discontinued": false,
      "description": "Line number of each line in multiple responses in a signed order summary."
    },
    {
      "index": 12,
      "name": "ORD_SUMMARY",
      "type": "VARCHAR",
      "discontinued": false,
      "description": "The summary sentence for the order."
    }
  ]
}
