{
  "table_name": "PAT_CONF_ADDL_ADDR_INFO",
  "description": "Additional Confidential Address Info.",
  "primary_key": {
    "column_name": "PAT_ID",
    "ordinal_position": "1"
  },
  "columns": [
    {
      "index": 2,
      "name": "PAT_ID",
      "type": "VARCHAR",
      "discontinued": false,
      "description": "The unique ID of the patient record for this row. This column is frequently used to link to the PATIENT table."
    },
    {
      "index": 7,
      "name": "LINE",
      "type": "INTEGER",
      "discontinued": false,
      "description": "The line number for the information associated with this record. Multiple pieces of information can be associated with this record."
    },
    {
      "index": 12,
      "name": "CONF_ADDL_ADDR_FIELD_C_NAME",
      "type": "VARCHAR",
      "discontinued": false,
      "description": "The type of additional confidential address data (floor, unit, building name, etc.) stored in the related field (I EPT 562).\n\n\nMay contain organization-specific values: No\n\n\n Category Entries: \n\n\nStreet address\n\n\nCity\n\n\nState\n\n\nZIP code\n\n\nCounty\n\n\nCountry\n\n\nHouse number\n\n\nDistrict\n\n\nBuilding name\n\n\nFloor\n\n\nUnit"
    },
    {
      "index": 30,
      "name": "CONF_ADDL_ADDR_DATA",
      "type": "VARCHAR",
      "discontinued": false,
      "description": "The additional confidential address data that the related \"type\" (I EPT 561) line applies to."
    }
  ]
}
