{
  "table_name": "PB_ACCT_TX_PLN_GRP",
  "description": "The PB_ACCT_TX_PLN_GRP table includes a list of employer groups associated with a premium billing account transaction.",
  "primary_key": {
    "column_name": "PB_ACT_TX_ID",
    "ordinal_position": "1"
  },
  "columns": [
    {
      "index": 2,
      "name": "PB_ACT_TX_ID",
      "type": "VARCHAR",
      "discontinued": false,
      "description": "The unique ID of the premium account transaction."
    },
    {
      "index": 7,
      "name": "LINE",
      "type": "INTEGER",
      "discontinued": false,
      "description": "Line counter of the employer group associated with the premium account transaction."
    },
    {
      "index": 12,
      "name": "PLAN_GRP_ID",
      "type": "VARCHAR",
      "discontinued": false,
      "description": "The unique ID of the employer group associated with the transaction."
    },
    {
      "index": 17,
      "name": "PLAN_GRP_ID_PLAN_GRP_NAME",
      "type": "VARCHAR",
      "discontinued": false,
      "description": "The name of the employer group record"
    }
  ]
}
