{
  "table_name": "PROC_INFO_SECTION_AUD",
  "description": "This table holds the procedure information navigator section audit information.",
  "primary_key": {
    "column_name": "SUMMARY_BLOCK_ID",
    "ordinal_position": "1"
  },
  "columns": [
    {
      "index": 2,
      "name": "SUMMARY_BLOCK_ID",
      "type": "NUMERIC",
      "discontinued": false,
      "description": "The unique identifier for the Episode."
    },
    {
      "index": 7,
      "name": "LINE",
      "type": "INTEGER",
      "discontinued": false,
      "description": "The line number for the information associated with this record. Multiple pieces of information can be associated with this record."
    },
    {
      "index": 12,
      "name": "AN_AUD_PROC_ID",
      "type": "NUMERIC",
      "discontinued": false,
      "description": "Contains audit trail information on procedure."
    },
    {
      "index": 17,
      "name": "AN_AUD_PROC_DATE",
      "type": "DATETIME",
      "discontinued": false,
      "description": "Contains audit trail information on procedure date."
    },
    {
      "index": 22,
      "name": "AN_AUD_PROC_PRE_DX_ID",
      "type": "NUMERIC",
      "discontinued": false,
      "description": "Contains audit trail information on pre-op diagnosis."
    },
    {
      "index": 27,
      "name": "AN_AUD_PROC_TIME",
      "type": "DATETIME (Local)",
      "discontinued": false,
      "description": "Contains audit trail information on procedure time."
    },
    {
      "index": 32,
      "name": "AN_AUD_PROC_COMMENT",
      "type": "VARCHAR",
      "discontinued": false,
      "description": "Contains audit trail information on procedure comment."
    },
    {
      "index": 37,
      "name": "AN_AUD_PROC_USER_ID",
      "type": "VARCHAR",
      "discontinued": false,
      "description": "Contains audit trail information on documenting user."
    },
    {
      "index": 42,
      "name": "AN_AUD_PROC_EDITED_UTC_DTTM",
      "type": "DATETIME (UTC)",
      "discontinued": false,
      "description": "Contains audit trail information on when procedure information was edited."
    }
  ]
}
