{
  "table_name": "SOCIAL_CARE_EPS_UPDTE_HX",
  "description": "Update history for Social Care specific episode data.",
  "primary_key": {
    "column_name": "SUMMARY_BLOCK_ID",
    "ordinal_position": "1"
  },
  "columns": [
    {
      "index": 2,
      "name": "SUMMARY_BLOCK_ID",
      "type": "NUMERIC",
      "discontinued": false,
      "description": "The unique identifier for the episode record."
    },
    {
      "index": 7,
      "name": "LINE",
      "type": "INTEGER",
      "discontinued": false,
      "description": "The line number for the information associated with this record. Multiple pieces of information can be associated with this record."
    },
    {
      "index": 12,
      "name": "SC_UPDATE_INSTANT_DTTM",
      "type": "DATETIME (UTC)",
      "discontinued": false,
      "description": "The instant the episode was updated."
    },
    {
      "index": 17,
      "name": "SC_UPDATE_USER_ID",
      "type": "VARCHAR",
      "discontinued": false,
      "description": "The unique ID of the user who updated the episode"
    },
    {
      "index": 22,
      "name": "SC_UPDATE_RESP_ID",
      "type": "VARCHAR",
      "discontinued": false,
      "description": "The unique ID of the responsible user when this line was updated."
    }
  ]
}
