{
  "table_name": "TRANSPLANT_DNRREL",
  "description": "Table for the intended recipient and relation of donor to the recipient.",
  "primary_key": {
    "column_name": "EPISODE_ID",
    "ordinal_position": "1"
  },
  "columns": [
    {
      "index": 2,
      "name": "EPISODE_ID",
      "type": "NUMERIC",
      "discontinued": false,
      "description": "The transplant episode record ID."
    },
    {
      "index": 7,
      "name": "LINE",
      "type": "INTEGER",
      "discontinued": false,
      "description": "The line number for the information associated with this record. Multiple pieces of information can be associated with this record."
    },
    {
      "index": 12,
      "name": "TX_DNR_REL_C_NAME",
      "type": "VARCHAR",
      "discontinued": false,
      "description": "This item indicates how the donor is related to the intended recipient. E.g. \"Parent\" indicates that the donor is a parent to the recipient.\n\n\nMay contain organization-specific values: Yes\n\n\n Category Entries: \n\n\nMother - Biological\n\n\nFather - Biological\n\n\nBrother - Biological\n\n\nSister - Biological\n\n\nTwin Brother - Biological\n\n\nTwin Sister - Biological\n\n\nHalf Brother - Biological\n\n\nHalf Sister - Biological\n\n\nSon - Biological\n\n\nDaughter - Biological\n\n\nRelated Other - Biological\n\n\nDomino - Biological\n\n\nNon-Domino Therapeutic - Biological\n\n\nSpouse - Non-Biological\n\n\nLife Partner - Non-Biological\n\n\nPaired Donation - Non-Biological\n\n\nLiving/Deceased Donation - Non-Biological\n\n\nAnonymous - Non-Biological\n\n\nAnonymous Humanitarian - Non-Biological\n\n\nAnonymous Directed - Non-Biological\n\n\nDomino - Non-Biological\n\n\nNon-Domino Therapeutic - Non-Biological\n\n\nOther - Non-Biological"
    }
  ]
}
