{
  "table_name": "UNOS_DIAB_TREATMNT",
  "description": "For a donor with diabetes, this indicates the treatment administered.",
  "primary_key": {
    "column_name": "REGISTRY_DATA_ID",
    "ordinal_position": "1"
  },
  "columns": [
    {
      "index": 2,
      "name": "REGISTRY_DATA_ID",
      "type": "NUMERIC",
      "discontinued": false,
      "description": "The unique identifier for the registry data record."
    },
    {
      "index": 7,
      "name": "LINE",
      "type": "INTEGER",
      "discontinued": false,
      "description": "The line number for the information associated with this record. Multiple pieces of information can be associated with this record."
    },
    {
      "index": 12,
      "name": "UNOS_DIAB_TREAT_C_NAME",
      "type": "VARCHAR",
      "discontinued": false,
      "description": "If the donor had diabetes prior to donation, the type of treatment the donor received.\n\n\nMay contain organization-specific values: No\n\n\n Category Entries: \n\n\nInsulin\n\n\nOral Hypoglycemic Agent\n\n\nDiet"
    }
  ]
}
