{
  "table_name": "VAR_CONTACT",
  "description": "This table contains the contact specific information for each variance record.",
  "primary_key": {
    "column_name": "VARIANCE_ID",
    "ordinal_position": "1"
  },
  "columns": [
    {
      "index": 2,
      "name": "VARIANCE_ID",
      "type": "VARCHAR",
      "discontinued": false,
      "description": "The unique ID for the variance record."
    },
    {
      "index": 7,
      "name": "CONTACT_DATE_REAL",
      "type": "FLOAT",
      "discontinued": false,
      "description": "The internal contact date for this variance record."
    },
    {
      "index": 12,
      "name": "CONTACT_DATE",
      "type": "DATETIME",
      "discontinued": false,
      "description": "The date of this contact in calendar format."
    },
    {
      "index": 17,
      "name": "IMPACT_C_NAME",
      "type": "VARCHAR",
      "discontinued": false,
      "description": "The impact rating for this variance contact.\n\n\nMay contain organization-specific values: Yes"
    },
    {
      "index": 23,
      "name": "LAST_UPD_USER_ID",
      "type": "VARCHAR",
      "discontinued": false,
      "description": "The unique ID of the user to last update this contact."
    },
    {
      "index": 28,
      "name": "LAST_UPDATE_TIME",
      "type": "DATETIME (Local)",
      "discontinued": false,
      "description": "The instance this contact was last updated."
    },
    {
      "index": 33,
      "name": "CONTACT_NUM",
      "type": "VARCHAR",
      "discontinued": false,
      "description": "Contact number for the variance contact."
    },
    {
      "index": 38,
      "name": "INSTANT_OF_ENT_DTTM",
      "type": "DATETIME (Local)",
      "discontinued": false,
      "description": "The instant of entry."
    },
    {
      "index": 43,
      "name": "READING_CAREPLAN_CSN_ID",
      "type": "NUMERIC",
      "discontinued": false,
      "description": "Links to the care plan contact that this variance was documented under"
    },
    {
      "index": 48,
      "name": "VARIANCE_COMMENT",
      "type": "VARCHAR",
      "discontinued": false,
      "description": "The comment added to a variance on a care plan."
    }
  ]
}
